ds_tools/__init__.py
ds_tools/distance.py
ds_tools/ds_tool.py
ds_tools/metrics.py
ds_tools/models.py
dscience_tools-2.3.2.dist-info/licenses/LICENSE
dscience_tools-2.3.2.dist-info/licenses/LICENSE-NC.txt
dscience_tools-2.3.2.dist-info/METADATA
dscience_tools-2.3.2.dist-info/WHEEL
dscience_tools-2.3.2.dist-info/top_level.txt
dscience_tools-2.3.2.dist-info/RECORD
