Metadata-Version: 2.4
Name: dscience_tools
Version: 2.3.2
Summary: DSTools: Data Science Tools Library
Home-page: https://github.com/s-kav/ds_tools
Author: Sergii Kavun
Author-email: Sergii Kavun <kavserg@gmail.com>
Maintainer-email: Sergii Kavun <kavserg@gmail.com>
License: PolyForm-Noncommercial-1.0.0 OR Commercial
Project-URL: Homepage, https://github.com/s-kav/ds_tools
Project-URL: Documentation, https://s-kav.github.io/ds_tools/
Project-URL: Repository, https://github.com/s-kav/ds_tools.git
Project-URL: Source Code, https://github.com/s-kav/ds_tools/tree/main/src
Project-URL: Bug Tracker, https://github.com/s-kav/ds_tools/issues
Classifier: Intended Audience :: Developers
Classifier: Intended Audience :: Information Technology
Classifier: Intended Audience :: Science/Research
Classifier: Natural Language :: English
Classifier: Operating System :: OS Independent
Classifier: Programming Language :: Python
Classifier: Programming Language :: Python :: 3
Classifier: Programming Language :: Python :: 3 :: Only
Classifier: Programming Language :: Python :: 3.6
Classifier: Topic :: Scientific/Engineering :: Artificial Intelligence
Classifier: Topic :: Scientific/Engineering :: Information Analysis
Classifier: Topic :: Scientific/Engineering :: Mathematics
Requires-Python: >=3.6.0
License-File: LICENSE
License-File: LICENSE-NC.txt
Requires-Dist: pandas<=2.2.3,>=0.25.0
Requires-Dist: numpy<=2.2.0,>=1.22.0
Provides-Extra: test
Requires-Dist: pytest; extra == "test"
Requires-Dist: pytest-cov; extra == "test"
Requires-Dist: pytest-mock; extra == "test"
Provides-Extra: performance
Requires-Dist: cupy-cuda13x; extra == "performance"
Requires-Dist: numba; extra == "performance"
Provides-Extra: lint
Requires-Dist: black==25.1.0; extra == "lint"
Requires-Dist: ruff==0.12.12; extra == "lint"
Dynamic: license-file
